{"Tigers_vs_Guardians": {"home_team": "Tigers", "away_team": "Guardians", "odds_history": [{"home_team_odds": -140.84507042253523, "away_team_odds": 110.00000000000001}, {"home_team_odds": 110.00000000000001, "away_team_odds": -129.87012987012986}]}, "White Sox_vs_Phillies": {"home_team": "White Sox", "away_team": "Phillies", "odds_history": [{"home_team_odds": 104.99999999999999, "away_team_odds": -125.0}, {"home_team_odds": -129.87012987012986, "away_team_odds": 110.00000000000001}]}, "Reds_vs_Rays": {"home_team": "Reds", "away_team": "Rays", "odds_history": [{"home_team_odds": 110.00000000000001, "away_team_odds": -129.87012987012986}]}, "Marlins_vs_Giants": {"home_team": "Marlins", "away_team": "Giants", "odds_history": [{"home_team_odds": -114.94252873563217, "away_team_odds": -105.26315789473685}]}, "Nationals_vs_Orioles": {"home_team": "Nationals", "away_team": "Orioles", "odds_history": [{"home_team_odds": 125.0, "away_team_odds": -144.92753623188406}]}, "Yankees_vs_Angels": {"home_team": "Yankees", "away_team": "Angels", "odds_history": [{"home_team_odds": -153.84615384615387, "away_team_odds": 135.0}]}, "Red Sox_vs_Twins": {"home_team": "Red Sox", "away_team": "Twins", "odds_history": [{"home_team_odds": -105.26315789473685, "away_team_odds": -114.94252873563217}]}, "Royals_vs_Rangers": {"home_team": "Royals", "away_team": "Rangers", "odds_history": [{"home_team_odds": 104.99999999999999, "away_team_odds": -125.0}]}, "Cardinals_vs_Diamondbacks": {"home_team": "Cardinals", "away_team": "Diamondbacks", "odds_history": [{"home_team_odds": -163.93442622950818, "away_team_odds": 140.0}]}}